thread/__init__.py
thread/__main__.py
thread/__version__.py
thread/_types.py
thread/cli.py
thread/decorators/__init__.py
thread/decorators/_processor.py
thread/decorators/_threaded.py
thread/exceptions.py
thread/py.typed
thread/thread.py
thread/utils/__init__.py
thread/utils/algorithm.py
thread/utils/config.py
thread/utils/meta.py
thread/version.py
thread-2.0.3.dist-info/LICENSE.txt
thread-2.0.3.dist-info/METADATA
thread-2.0.3.dist-info/WHEEL
thread-2.0.3.dist-info/entry_points.txt
thread-2.0.3.dist-info/RECORD
