Metadata-Version: 2.1
Name: thread
Version: 2.0.3
Summary: Threading module extension
License: BSD-3-Clause
Keywords: thread,threading,extension,multiprocessing
Author: Alex
Author-email: contact@ngjx.org
Requires-Python: >=3.9,<4.0
Classifier: Development Status :: 4 - Beta
Classifier: Intended Audience :: Developers
Classifier: License :: OSI Approved :: BSD License
Classifier: Operating System :: OS Independent
Classifier: Programming Language :: Python
Classifier: Programming Language :: Python :: 3
Classifier: Programming Language :: Python :: 3.9
Classifier: Programming Language :: Python :: 3.10
Classifier: Programming Language :: Python :: 3.11
Classifier: Programming Language :: Python :: 3.12
Classifier: Programming Language :: Python :: 3 :: Only
Classifier: Programming Language :: Python :: Implementation :: CPython
Classifier: Topic :: Software Development
Classifier: Typing :: Typed
Requires-Dist: importlib-metadata (>=4.4) ; python_version < "3.10"
Requires-Dist: typing-extensions (>=4.9.0,<5.0.0)
Project-URL: Bug Tracker, https://github.com/python-thread/thread/issues
Project-URL: Documentation, https://thread.ngjx.org/docs/v2.0.3
Project-URL: Download, https://pypi.org/project/thread/#files
Project-URL: Homepage, https://thread.ngjx.org
Project-URL: Release Notes, https://github.com/python-thread/thread/releases
Project-URL: Source, https://github.com/python-thread/thread
